Workbook

Sheet Orders
A1: order_id | B1: customer_id | C1: order_date | D1: promised_delivery_time | E1: actual_delivery_time | F1: delivery_status | G1: payment_method | H1: delivery_partner_id | I1: store_id
A2: 1961864118 | B2: 30065862 | C2: 45490.357 | D2: 45490.369 | E2: 45490.366 | F2: On Time | G2: Cash | H2: 63230 | I2: 4771
A3: 1549769649 | B3: 9573071 | C3: 45440.552 | D3: 45440.559 | E3: 45440.561 | F3: On Time | G3: Cash | H3: 14983 | I3: 7534
A4: 9185164487 | B4: 45477575 | C4: 45558.547 | D4: 45558.559 | E4: 45558.562 | F4: On Time | G4: UPI | H4: 39859 | I4: 9886
A5: 9644738826 | B5: 88067569 | C5: 45254.678 | D5: 45254.691 | E5: 45254.69 | F5: On Time | G5: Card | H5: 61497 | I5: 7917
A6: 5427684290 | B6: 83298567 | C6: 45250.209 | D6: 45250.221 | E6: 45250.221 | F6: On Time | G6: Cash | H6: 84315 | I6: 2741
A7: 3265154092 | B7: 43367112 | C7: 45003.687 | D7: 45003.701 | E7: 45003.701 | F7: On Time | G7: UPI | H7: 554 | I7: 3442
A8: 4898355547 | B8: 13284996 | C8: 45032.785 | D8: 45032.793 | E8: 45032.793 | F8: On Time | G8: Card | H8: 14630 | I8: 1318
A9: 6568151549 | B9: 88866835 | C9: 45382.269 | D9: 45382.276 | E9: 45382.278 | F9: On Time | G9: Cash | H9: 67714 | I9: 115
A10: 6006693867 | B10: 24496983 | C10: 45120.993 | D10: 45121.002 | E10: 45121.004 | F10: On Time | G10: Card | H10: 91362 | I10: 9021
A11: 374186990 | B11: 52215833 | C11: 45147.054 | D11: 45147.068 | E11: 45147.073 | F11: Slightly Delayed | G11: Wallet | H11: 77203 | I11: 7955
A12: 4455336265 | B12: 43431724 | C12: 45168.817 | D12: 45168.824 | E12: 45168.823 | F12: On Time | G12: UPI | H12: 64046 | I12: 3784
A13: 3539286337 | B13: 77559557 | C13: 45041.856 | D13: 45041.864 | E13: 45041.861 | F13: On Time | G13: Wallet | H13: 94899 | I13: 2463
... A5001: 2494813730 | B5001: 28663279 | C5001: 45161.503 | D5001: 45161.514 | E5001: 45161.515 | F5001: On Time | G5001: Card | H5001: 32851 | I5001: 5588

Sheet Order_items
A1: order_id | B1: product_id | C1: quantity | D1: unit_price | E1: Sales
A2: 1961864118 | B2: 642612 | C2: 3 | D2: 517.03 | E2: =C2*D2 -> 1551.09
A3: 1549769649 | B3: 378676 | C3: 1 | D3: 881.42 | E3: =C3*D3 -> 881.42
A4: 9185164487 | B4: 741341 | C4: 2 | D4: 923.84 | E4: =C4*D4 -> 1847.68
A5: 9644738826 | B5: 561860 | C5: 1 | D5: 874.78 | E5: =C5*D5 -> 874.78
A6: 5427684290 | B6: 602241 | C6: 2 | D6: 976.55 | E6: =C6*D6 -> 1953.1
A7: 3265154092 | B7: 681063 | C7: 1 | D7: 321.28 | E7: =C7*D7 -> 321.28
A8: 4898355547 | B8: 56589 | C8: 3 | D8: 517.77 | E8: =C8*D8 -> 1553.31
A9: 6568151549 | B9: 500739 | C9: 2 | D9: 359.98 | E9: =C9*D9 -> 719.96
A10: 6006693867 | B10: 490939 | C10: 1 | D10: 80.25 | E10: =C10*D10 -> 80.25
A11: 374186990 | B11: 760828 | C11: 2 | D11: 563.45 | E11: =C11*D11 -> 1126.9
A12: 4455336265 | B12: 753354 | C12: 3 | D12: 423.56 | E12: =C12*D12 -> 1270.68
A13: 3539286337 | B13: 684939 | C13: 1 | D13: 727.95 | E13: =C13*D13 -> 727.95
... A5001: 2494813730 | B5001: 136533 | C5001: 1 | D5001: 826.21 | E5001: =C5001*D5001 -> 826.21

Sheet Products
A1: product_id | B1: product_name | C1: category | D1: brand | E1: price | F1: mrp | G1: margin_percentage | H1: shelf_life_days | I1: min_stock_level | J1: max_stock_level
A2: 153019 | B2: Onions | C2: Fruits & Vegetables | D2: Aurora LLC | E2: 947.95 | F2: 1263.93 | G2: 25 | H2: 3 | I2: 13 | J2: 88
A3: 11422 | B3: Potatoes | C3: Fruits & Vegetables | D3: Ramaswamy-Tata | E3: 127.16 | F3: 169.55 | G3: 25 | H3: 3 | I3: 20 | J3: 65
A4: 669378 | B4: Potatoes | C4: Fruits & Vegetables | D4: Chadha and Sons | E4: 212.14 | F4: 282.85 | G4: 25 | H4: 3 | I4: 23 | J4: 70
A5: 848226 | B5: Tomatoes | C5: Fruits & Vegetables | D5: Barad and Sons | E5: 209.59 | F5: 279.45 | G5: 25 | H5: 3 | I5: 10 | J5: 51
A6: 890623 | B6: Onions | C6: Fruits & Vegetables | D6: Sangha, Nagar and Varty | E6: 354.52 | F6: 472.69 | G6: 25 | H6: 3 | I6: 27 | J6: 55
A7: 965755 | B7: Bananas | C7: Fruits & Vegetables | D7: Doshi, Sarraf and Sama | E7: 532.57 | F7: 710.09 | G7: 25 | H7: 3 | I7: 21 | J7: 91
A8: 222892 | B8: Tomatoes | C8: Fruits & Vegetables | D8: Ramakrishnan-Ghose | E8: 869.22 | F8: 1158.96 | G8: 25 | H8: 3 | I8: 28 | J8: 88
A9: 516376 | B9: Onions | C9: Fruits & Vegetables | D9: Agarwal-Dhar | E9: 877.43 | F9: 1169.91 | G9: 25 | H9: 3 | I9: 21 | J9: 71
A10: 39154 | B10: Mangoes | C10: Fruits & Vegetables | D10: Suresh, Bose and Bajwa | E10: 946.86 | F10: 1262.48 | G10: 25 | H10: 3 | I10: 21 | J10: 84
A11: 34186 | B11: Mangoes | C11: Fruits & Vegetables | D11: Mandal-Kar | E11: 925.65 | F11: 1234.2 | G11: 25 | H11: 3 | I11: 27 | J11: 74
A12: 196719 | B12: Bananas | C12: Fruits & Vegetables | D12: Yogi Group | E12: 217.5 | F12: 290 | G12: 25 | H12: 3 | I12: 15 | J12: 91
A13: 478531 | B13: Carrots | C13: Fruits & Vegetables | D13: Uppal Group | E13: 825.46 | F13: 1100.61 | G13: 25 | H13: 3 | I13: 24 | J13: 90
... A269: 114414 | B269: Vitamins | C269: Pharmacy | D269: Kara-Golla | E269: 832.06 | F269: 1040.07 | G269: 20 | H269: 365 | I269: 26 | J269: 66

Sheet Data_Analysis
A1: Order_ID | B1: Order_Date | C1: Product_ID | D1: Product_Name | E1: Category | F1: Brand | G1: Quantity | H1: Price | I1: Sales | J1: Payment_Method | K1: Order_Yearly | L1: Order_Monthly
A2: =(Orders!A2) -> 1961864118 | B2: {=_xlfn.XLOOKUP(A2,Orders!A:A,Orders!C:C)} -> 45490.357 | C2: =Order_items!B2 -> 642612 | D2: {=_xlfn.XLOOKUP(C2,Products!A:A,Products!B:B,"")} -> Pet Treats | E2: {=_xlfn.XLOOKUP(C2,Products!A:A,Products!C:C,"")} -> Pet Care | F2: {=_xlfn.XLOOKUP(C2,Products!A:A,Products!D:D,"")} -> Pillay-Ahuja | G2: =Order_items!C2 -> 3 | H2: =Order_items!D2 -> 517.03 | I2: =Order_items!E2 -> 1551.09 | J2: {=_xlfn.XLOOKUP(A2,Orders!A:A,Orders!G:G,"")} -> Cash | K2: =YEAR(B2) -> 2024 | L2: =Text(B2,"MMM") -> Jul
A3: =(Orders!A3) -> 1549769649 | B3: {=_xlfn.XLOOKUP(A3, Orders!A:A,Orders!C:C)} -> 45440.552 | C3: =Order_items!B3 -> 378676 | D3: {=_xlfn.XLOOKUP(C3,Products!A:A,Products!B:B,"")} -> Orange Juice | E3: {=_xlfn.XLOOKUP(C3,Products!A:A,Products!C:C,"")} -> Cold Drinks & Juices | F3: {=_xlfn.XLOOKUP(C3,Products!A:A,Products!D:D,"")} -> Baral-Kamdar | G3: =Order_items!C3 -> 1 | H3: =Order_items!D3 -> 881.42 | I3: =Order_items!E3 -> 881.42 | J3: {=_xlfn.XLOOKUP(A3,Orders!A:A,Orders!G:G,"")} -> Cash | K3: =YEAR(B3) -> 2024 | L3: =Text(B3,"MMM") -> May
A4: =(Orders!A4) -> 9185164487 | B4: {=_xlfn.XLOOKUP(A4, Orders!A:A,Orders!C:C)} -> 45558.547 | C4: =Order_items!B4 -> 741341 | D4: {=_xlfn.XLOOKUP(C4,Products!A:A,Products!B:B,"")} -> Eggs | E4: {=_xlfn.XLOOKUP(C4,Products!A:A,Products!C:C,"")} -> Dairy & Breakfast | F4: {=_xlfn.XLOOKUP(C4,Products!A:A,Products!D:D,"")} -> Prasad LLC | G4: =Order_items!C4 -> 2 | H4: =Order_items!D4 -> 923.84 | I4: =Order_items!E4 -> 1847.68 | J4: {=_xlfn.XLOOKUP(A4,Orders!A:A,Orders!G:G,"")} -> UPI | K4: =YEAR(B4) -> 2024 | L4: =Text(B4,"MMM") -> Sep
A5: =(Orders!A5) -> 9644738826 | B5: {=_xlfn.XLOOKUP(A5, Orders!A:A,Orders!C:C)} -> 45254.678 | C5: =Order_items!B5 -> 561860 | D5: {=_xlfn.XLOOKUP(C5,Products!A:A,Products!B:B,"")} -> Orange Juice | E5: {=_xlfn.XLOOKUP(C5,Products!A:A,Products!C:C,"")} -> Cold Drinks & Juices | F5: {=_xlfn.XLOOKUP(C5,Products!A:A,Products!D:D,"")} -> Gupta Ltd | G5: =Order_items!C5 -> 1 | H5: =Order_items!D5 -> 874.78 | I5: =Order_items!E5 -> 874.78 | J5: {=_xlfn.XLOOKUP(A5,Orders!A:A,Orders!G:G,"")} -> Card | K5: =YEAR(B5) -> 2023 | L5: =Text(B5,"MMM") -> Nov
A6: =(Orders!A6) -> 5427684290 | B6: {=_xlfn.XLOOKUP(A6, Orders!A:A,Orders!C:C)} -> 45250.209 | C6: =Order_items!B6 -> 602241 | D6: {=_xlfn.XLOOKUP(C6,Products!A:A,Products!B:B,"")} -> Nuts | E6: {=_xlfn.XLOOKUP(C6,Products!A:A,Products!C:C,"")} -> Snacks & Munchies | F6: {=_xlfn.XLOOKUP(C6,Products!A:A,Products!D:D,"")} -> Bahl-Pau | G6: =Order_items!C6 -> 2 | H6: =Order_items!D6 -> 976.55 | I6: =Order_items!E6 -> 1953.1 | J6: {=_xlfn.XLOOKUP(A6,Orders!A:A,Orders!G:G,"")} -> Cash | K6: =YEAR(B6) -> 2023 | L6: =Text(B6,"MMM") -> Nov
A7: =(Orders!A7) -> 3265154092 | B7: {=_xlfn.XLOOKUP(A7, Orders!A:A,Orders!C:C)} -> 45003.687 | C7: =Order_items!B7 -> 681063 | D7: {=_xlfn.XLOOKUP(C7,Products!A:A,Products!B:B,"")} -> Mango Drink | E7: {=_xlfn.XLOOKUP(C7,Products!A:A,Products!C:C,"")} -> Cold Drinks & Juices | F7: {=_xlfn.XLOOKUP(C7,Products!A:A,Products!D:D,"")} -> Dass and Sons | G7: =Order_items!C7 -> 1 | H7: =Order_items!D7 -> 321.28 | I7: =Order_items!E7 -> 321.28 | J7: {=_xlfn.XLOOKUP(A7,Orders!A:A,Orders!G:G,"")} -> UPI | K7: =YEAR(B7) -> 2023 | L7: =Text(B7,"MMM") -> Mar
A8: =(Orders!A8) -> 4898355547 | B8: {=_xlfn.XLOOKUP(A8, Orders!A:A,Orders!C:C)} -> 45032.785 | C8: =Order_items!B8 -> 56589 | D8: {=_xlfn.XLOOKUP(C8,Products!A:A,Products!B:B,"")} -> Vitamins | E8: {=_xlfn.XLOOKUP(C8,Products!A:A,Products!C:C,"")} -> Pharmacy | F8: {=_xlfn.XLOOKUP(C8,Products!A:A,Products!D:D,"")} -> Pai, Kashyap and Ramachandran | G8: =Order_items!C8 -> 3 | H8: =Order_items!D8 -> 517.77 | I8: =Order_items!E8 -> 1553.31 | J8: {=_xlfn.XLOOKUP(A8,Orders!A:A,Orders!G:G,"")} -> Card | K8: =YEAR(B8) -> 2023 | L8: =Text(B8,"MMM") -> Apr
A9: =(Orders!A9) -> 6568151549 | B9: {=_xlfn.XLOOKUP(A9, Orders!A:A,Orders!C:C)} -> 45382.269 | C9: =Order_items!B9 -> 500739 | D9: {=_xlfn.XLOOKUP(C9,Products!A:A,Products!B:B,"")} -> Bread | E9: {=_xlfn.XLOOKUP(C9,Products!A:A,Products!C:C,"")} -> Dairy & Breakfast | F9: {=_xlfn.XLOOKUP(C9,Products!A:A,Products!D:D,"")} -> Aggarwal Group | G9: =Order_items!C9 -> 2 | H9: =Order_items!D9 -> 359.98 | I9: =Order_items!E9 -> 719.96 | J9: {=_xlfn.XLOOKUP(A9,Orders!A:A,Orders!G:G,"")} -> Cash | K9: =YEAR(B9) -> 2024 | L9: =Text(B9,"MMM") -> Mar
A10: =(Orders!A10) -> 6006693867 | B10: {=_xlfn.XLOOKUP(A10, Orders!A:A,Orders!C:C)} -> 45120.993 | C10: =Order_items!B10 -> 490939 | D10: {=_xlfn.XLOOKUP(C10,Products!A:A,Products!B:B,"")} -> Lotion | E10: {=_xlfn.XLOOKUP(C10,Products!A:A,Products!C:C,"")} -> Personal Care | F10: {=_xlfn.XLOOKUP(C10,Products!A:A,Products!D:D,"")} -> Roy, Barad and De | G10: =Order_items!C10 -> 1 | H10: =Order_items!D10 -> 80.25 | I10: =Order_items!E10 -> 80.25 | J10: {=_xlfn.XLOOKUP(A10,Orders!A:A,Orders!G:G,"")} -> Card | K10: =YEAR(B10) -> 2023 | L10: =Text(B10,"MMM") -> Jul
A11: =(Orders!A11) -> 374186990 | B11: {=_xlfn.XLOOKUP(A11, Orders!A:A,Orders!C:C)} -> 45147.054 | C11: =Order_items!B11 -> 760828 | D11: {=_xlfn.XLOOKUP(C11,Products!A:A,Products!B:B,"")} -> Pet Treats | E11: {=_xlfn.XLOOKUP(C11,Products!A:A,Products!C:C,"")} -> Pet Care | F11: {=_xlfn.XLOOKUP(C11,Products!A:A,Products!D:D,"")} -> Khurana, Khosla and Yohannan | G11: =Order_items!C11 -> 2 | H11: =Order_items!D11 -> 563.45 | I11: =Order_items!E11 -> 1126.9 | J11: {=_xlfn.XLOOKUP(A11,Orders!A:A,Orders!G:G,"")} -> Wallet | K11: =YEAR(B11) -> 2023 | L11: =Text(B11,"MMM") -> Aug
A12: =(Orders!A12) -> 4455336265 | B12: {=_xlfn.XLOOKUP(A12, Orders!A:A,Orders!C:C)} -> 45168.817 | C12: =Order_items!B12 -> 753354 | D12: {=_xlfn.XLOOKUP(C12,Products!A:A,Products!B:B,"")} -> Shampoo | E12: {=_xlfn.XLOOKUP(C12,Products!A:A,Products!C:C,"")} -> Personal Care | F12: {=_xlfn.XLOOKUP(C12,Products!A:A,Products!D:D,"")} -> Sant-Mahajan | G12: =Order_items!C12 -> 3 | H12: =Order_items!D12 -> 423.56 | I12: =Order_items!E12 -> 1270.68 | J12: {=_xlfn.XLOOKUP(A12,Orders!A:A,Orders!G:G,"")} -> UPI | K12: =YEAR(B12) -> 2023 | L12: =Text(B12,"MMM") -> Aug
A13: =(Orders!A13) -> 3539286337 | B13: {=_xlfn.XLOOKUP(A13, Orders!A:A,Orders!C:C)} -> 45041.856 | C13: =Order_items!B13 -> 684939 | D13: {=_xlfn.XLOOKUP(C13,Products!A:A,Products!B:B,"")} -> Lotion | E13: {=_xlfn.XLOOKUP(C13,Products!A:A,Products!C:C,"")} -> Personal Care | F13: {=_xlfn.XLOOKUP(C13,Products!A:A,Products!D:D,"")} -> Sibal, Bhatnagar and Rajan | G13: =Order_items!C13 -> 1 | H13: =Order_items!D13 -> 727.95 | I13: =Order_items!E13 -> 727.95 | J13: {=_xlfn.XLOOKUP(A13,Orders!A:A,Orders!G:G,"")} -> Wallet | K13: =YEAR(B13) -> 2023 | L13: =Text(B13,"MMM") -> Apr
A14: =(Orders!A14) -> 9171116867 | B14: {=_xlfn.XLOOKUP(A14, Orders!A:A,Orders!C:C)} -> 45221.469 | C14: =Order_items!B14 -> 500739 | D14: {=_xlfn.XLOOKUP(C14,Products!A:A,Products!B:B,"")} -> Bread | E14: {=_xlfn.XLOOKUP(C14,Products!A:A,Products!C:C,"")} -> Dairy & Breakfast | F14: {=_xlfn.XLOOKUP(C14,Products!A:A,Products!D:D,"")} -> Aggarwal Group | G14: =Order_items!C14 -> 3 | H14: =Order_items!D14 -> 359.98 | I14: =Order_items!E14 -> 1079.94 | J14: {=_xlfn.XLOOKUP(A14,Orders!A:A,Orders!G:G,"")} -> Card | K14: =YEAR(B14) -> 2023 | L14: =Text(B14,"MMM") -> Oct
... A5001: =(Orders!A5001) -> 2494813730 | B5001: {=_xlfn.XLOOKUP(A5001, Orders!A:A,Orders!C:C)} -> 45161.503 | C5001: =Order_items!B5001 -> 136533 | D5001: {=_xlfn.XLOOKUP(C5001,Products!A:A,Products!B:B,"")} -> Eggs | E5001: {=_xlfn.XLOOKUP(C5001,Products!A:A,Products!C:C,"")} -> Dairy & Breakfast | F5001: {=_xlfn.XLOOKUP(C5001,Products!A:A,Products!D:D,"")} -> Raghavan, Magar and Shanker | G5001: =Order_items!C5001 -> 1 | H5001: =Order_items!D5001 -> 826.21 | I5001: =Order_items!E5001 -> 826.21 | J5001: {=_xlfn.XLOOKUP(A5001,Orders!A:A,Orders!G:G,"")} -> Card | K5001: =YEAR(B5001) -> 2023 | L5001: =Text(B5001,"MMM") -> Aug

Sheet Pivot_Tables
A1: Sales by Month | D1: Sales by Category | G1: Top 10 Products | J1: Sales by Brand | M1: Quantity by Category | P1: Payment Method

Sheet Dashbaord
C2: BLINKIT SALES DASHBOARD
B4: TOTAL SALES | C4: TOTAL ORDERS | D4: TOTAL QUANTITY | E4: AVG ORDER VALUE
B5: =SUM(Data_Analysis!I2:I1000) -> 4972415.4 | C5: =COUNT(Data_Analysis!A2:A1000) -> 5000 | D5: =SUM(Data_Analysis!G2:G1000) -> 10034 | E5: =B5/C5 -> 994.48309
